autotrader/SmartWebSocketV2.py
autotrader/__init__.py
autotrader/autotradingfunctions.py
autotrader/blackscholes.py
autotrader/datamodule.py
autotrader/discord_bot.py
autotrader/exceptions.py
autotrader/nsefunctions.py
autotrader/strategies.py
autotrading-0.9.0.dist-info/METADATA
autotrading-0.9.0.dist-info/WHEEL
autotrading-0.9.0.dist-info/top_level.txt
autotrading-0.9.0.dist-info/RECORD
