Metadata-Version: 2.1
Name: autotrading
Version: 0.9.0
Classifier: Programming Language :: Python :: 3
Classifier: Programming Language :: Python :: 3.6
Classifier: Programming Language :: Python :: 3.7
Classifier: Programming Language :: Python :: 3.8
Classifier: Programming Language :: Python :: 3.9
Requires-Dist: asttokens (==2.2.1)
Requires-Dist: backcall (==0.2.0)
Requires-Dist: certifi (==2022.12.7)
Requires-Dist: colorama (==0.4.6)
Requires-Dist: comm (==0.1.2)
Requires-Dist: decorator (==5.1.1)
Requires-Dist: discord.py (>=2.2.2)
Requires-Dist: entrypoints (==0.4)
Requires-Dist: executing (==1.2.0)
Requires-Dist: eod (==0.2.1)
Requires-Dist: fuzzywuzzy (==0.18.0)
Requires-Dist: idna (==3.4)
Requires-Dist: jedi (==0.18.2)
Requires-Dist: lxml (==4.9.2)
Requires-Dist: matplotlib-inline (==0.1.6)
Requires-Dist: nest-asyncio (==1.5.6)
Requires-Dist: numpy (==1.24.2)
Requires-Dist: packaging (==23.0)
Requires-Dist: pandas (==1.5.3)
Requires-Dist: parso (==0.8.3)
Requires-Dist: pickleshare (==0.7.5)
Requires-Dist: platformdirs (==2.6.2)
Requires-Dist: plotly (==5.14.1)
Requires-Dist: prompt-toolkit (==3.0.36)
Requires-Dist: psutil (==5.9.4)
Requires-Dist: pure-eval (==0.2.2)
Requires-Dist: Pygments (==2.14.0)
Requires-Dist: pyotp (==2.8.0)
Requires-Dist: python-dateutil (==2.8.2)
Requires-Dist: python-Levenshtein (==0.21.0)
Requires-Dist: pytz (==2022.7.1)
Requires-Dist: pywin32 (==305)
Requires-Dist: pyzmq (==25.0.0)
Requires-Dist: requests (==2.28.2)
Requires-Dist: scikit-learn (==1.2.2)
Requires-Dist: scipy (==1.10.1)
Requires-Dist: six (==1.16.0)
Requires-Dist: smartapi-python (==1.3.0)
Requires-Dist: spyder-kernels (>=2.2.1)
Requires-Dist: stack-data (==0.6.2)
Requires-Dist: tornado (==6.2)
Requires-Dist: traitlets (==5.8.1)
Requires-Dist: urllib3 (==1.26.14)
Requires-Dist: wcwidth (==0.2.6)
Requires-Dist: websocket-client (==1.5.1)
Requires-Dist: xlrd (==2.0.1)
Requires-Dist: yfinance (==0.2.14)
